evil_jea/__init__.py
evil_jea/cli.py
evil_jea/version.py
evil_jea-0.0.2.dist-info/LICENSE
evil_jea-0.0.2.dist-info/METADATA
evil_jea-0.0.2.dist-info/WHEEL
evil_jea-0.0.2.dist-info/entry_points.txt
evil_jea-0.0.2.dist-info/top_level.txt
evil_jea-0.0.2.dist-info/RECORD
