Metadata-Version: 2.1
Name: evil-jea
Version: 0.0.2
Summary: A small WinRM client designed for interacting with JEA endpoints.
Home-page: https://github.com/sashathomas/evil-jea
Download-URL: https://github.com/sashathomas/evil-jea/archive/0.0.2.tar.gz
Author: Sasha Thomas
Author-email: mathnerd2718@gmail.com
License: MIT
Classifier: Development Status :: 3 - Alpha
Classifier: Intended Audience :: Developers
Classifier: Topic :: Software Development :: Libraries
Classifier: License :: OSI Approved :: MIT License
Classifier: Programming Language :: Python :: 3.8
Requires-Python: >=3.11.0
License-File: LICENSE
Requires-Dist: click <8,>=7.0
